{
    "description": "Im Februar hat in Berlin das zweite HR BarCamp stattgefunden. Die Organisatoren Christoph Athanas und Jannis Tsalikis über ihr Tagungskonzept und die diesjährigen Themen. Herr Athanas, Herr Tsalikis, die Personaler haben das Programm der Tagung selbst bestimmt. Welche Themen waren besonders präsent, gab es da Schwerpunkte? Christoph Athanas: Recruiting ist ein ganz großes Thema, da",
    "og:type": "article",
    "og:title": "„Recruiting ist ein großes Thema“",
    "og:description": "Im Februar hat in Berlin das zweite HR BarCamp stattgefunden. Die Organisatoren Christoph Athanas und Jannis Tsalikis über ihr Tagungskonzept und die diesjährigen Themen. Herr Athanas, Herr Tsalikis, die Personaler haben das Programm der Tagung selbst bestimmt. Welche Themen waren besonders präsent, gab es da Schwerpunkte? Christoph Athanas: Recruiting ist ein ganz großes Thema, da",
    "og:url": "https://www.humanresourcesmanager.de/employer-branding/recruiting-ist-ein-grosses-thema/",
    "article:published_time": "2013-03-26T15:15:28+00:00",
    "article:modified_time": "2022-02-18T12:46:45+00:00",
    "keywords": [],
    "h1": "„Recruiting ist ein großes Thema“",
    "url": "https://www.humanresourcesmanager.de/employer-branding/recruiting-ist-ein-grosses-thema/",
    "time_crawled": "2024-12-13T15:30:30.369432",
    "text_html": "<html>\n <body>\n  <h1>\n   „Recruiting ist ein großes Thema“\n  </h1>\n  <p>\n   Im Februar hat in Berlin das zweite HR BarCamp stattgefunden. Die Organisatoren Christoph Athanas und Jannis Tsalikis über ihr Tagungskonzept und die diesjährigen Themen.\n  </p>\n  <p>\n   Herr Athanas, Herr Tsalikis, die Personaler haben das Programm der Tagung selbst bestimmt. Welche Themen waren besonders präsent, gab es da Schwerpunkte?\n  </p>\n  <p>\n   Christoph Athanas: Recruiting ist ein ganz großes Thema, da hatten wir Sessions wie Mobile Recruiting, transparentes Recruiting und Online-Assessments. Manches war eher technologielastig, anderes mehr ein Kulturthema. Ich selber habe eine Session mitgeleitet zur Frage, in welche Richtung HR geht und ob der Business Partner noch das Modell ist. Und dann gab es mit dem Thema Guerilla-Lernen einen neuen Zugang zur Personalentwicklung.\n  </p>\n  <p>\n   Jannis Tsalikis: Das fand ich eine wirklich spannende Session. Es ging darum, dass man eben nicht klassisch denkt: ‚Wir müssen den Leuten jetzt das und das beibringen’, sondern dass man von der Zielgruppe aus denkt. Dass man sich überlegt, in welchen Situationen man die Leute am besten erreichen kann, um nicht in den alten Stil von Frontalunterricht zu verfallen.\n  </p>\n  <p>\n   Was haben Sie außerdem noch als neu, als inspirierend wahrgenommen hier auf dem BarCamp? Oder war Ihnen alles schon bekannt?\n  </p>\n  <p>\n   Tsalikis: Wir als Veranstalter konnten natürlich gar nicht an allen Sessions teilnehmen. Aber dieses Guerilla-Lernen fand ich neu, darüber habe ich so noch nicht nachgedacht. Insgesamt ist es schön, dass es beim HR BarCamp eine gute Mischung gibt zwischen Dienstleistern und Praktikern, die Sessions geben.\n  </p>\n  <p>\n   Warum braucht es denn so eine Tagung wie das HR BarCamp?\n  </p>\n  <p>\n   Athanas: Es gibt einfach wenig Offline-Formate, die uns zugesagt haben, wo innovative Inhalte auch in innovativen Formaten diskutiert werden können.\n  </p>\n  <p>\n   Tsalikis: Vor allen Dingen waren wir es leid, den althergebrachten Stil der Konferenzen ertragen zu müssen. Man muss sich vergegenwärtigen, dass die Leute ja extrem beschäftigt sind und sich dann einen Tag freinehmen um Impulse zu bekommen. Und dann sind sie nach dem ersten Vortrag schon halb eingeschlafen, weil sie die Hälfte davon kennen, überhaupt nicht integriert werden und auch nicht unterhalten werden. So verliert man die Leute. Das kriegt man auf den Kongressen mit. Diese Zeit ist eigentlich auch vorbei. Gerade aufgrund der sozialen Medien gibt es Veränderungen, alles ist dialogischer geworden. Die Leute wollen miteinander reden und sich austauschen.\n  </p>\n  <p>\n   Demnach ließe sich vermuten, dass es eher die jüngeren, online-affineren Personaler sind, die zum HR BarCamp kommen?\n  </p>\n  <p>\n   Athanas: Das ist gemischt. Sicherlich ist der Altersschnitt hier schon eher jünger, aber das heißt nicht, dass hier nur die Generation Y dabei ist oder sich die Leute kollektiv bei Foursquare einchecken. Aufgeschlossen muss man sein. Aber das geht ja auch im höheren Alter.\n  </p>\n  <p>\n   Tsalikis: Es gab mal eine Debatte vor ein paar Jahren, wie altbacken und verstaubt doch die Personaler seien und das sie gar nicht in der Lage seien, Innovationen anzuschieben. Ich habe das nie so empfunden. Klar, ich bin auch in der Medienbranche tätig, da ist das eh eine ganz andere Sache. Aber auch auf Kongressen hab ich Leute kennengelernt, die in ihrem Fach Experten waren. Die haben viel zu tun, müssen sich ständig etwas Neues überlegen, viele von ihnen sind regelmäßig in Change-Situationen, bei denen sie zwischen Betriebsrat, Geschäftsführung und Mitarbeitern jonglieren müssen. Das ist eine Herausforderung. Vor allem wenn es auch noch Spaß machen soll.\n  </p>\n  <p>\n   Wie funktioniert denn die Organisation des HR BarCamps? Machen Sie das neben dem Hauptjob?\n  </p>\n  <p>\n   Tsalikis: Ja, das ist ein Hobby.\n  </p>\n  <p>\n   Athanas: Das läuft tatsächlich nebenbei. Es bringt aber auch so viel Spaß, dass wir das gerne auf uns nehmen.\n  </p>\n  <p>\n   Tsalikis: Ich hab auch einen Arbeitgeber, der das toleriert und gut findet. In der Regel findet die Organisation am Abend oder am Wochenende statt, aber wenn ich dann mal eine Pause länger ausdehnen muss, weil Christoph und ich uns noch mal austauschen müssen, dann drückt der ein Auge zu.\n  </p>\n  <p>\n   Können Sie schon einen Blick ins kommende Jahr werfen, wird es ein drittes HR BarCamp geben?\n  </p>\n  <p>\n   Tsalikis: Wir werden auf jeden Fall weitermachen. Das ist zwar für uns beide richtig anstrengend, aber es macht unglaublich Spaß und das Feedback ist super. Wir sind immer wieder überrascht, mit wie viel Begeisterung die Kollegen auf uns zukommen und sagen ‚Mensch das wurde aber auch Zeit’.\n  </p>\n  <p>\n   Athanas: Wir waren in diesem Jahr in zwei Tagen ausgebucht. Das ist Wahnsinn. Es waren dann 140 Teilnehmer, was ich gut finde. So hat das BarCamp eine sehr persönliche Atmosphäre und man kann mit vielen Leuten reden. Ich denke, es wird also auch im kommenden Jahr ein BarCamp geben, da bleiben wir dran.\n  </p>\n </body>\n</html>\n",
    "text": "„Recruiting ist ein großes Thema“\n\nIm Februar hat in Berlin das zweite HR BarCamp stattgefunden. Die Organisatoren Christoph Athanas und Jannis Tsalikis über ihr Tagungskonzept und die diesjährigen Themen.\n\nHerr Athanas, Herr Tsalikis, die Personaler haben das Programm der Tagung selbst bestimmt. Welche Themen waren besonders präsent, gab es da Schwerpunkte?\n\nChristoph Athanas: Recruiting ist ein ganz großes Thema, da hatten wir Sessions wie Mobile Recruiting, transparentes Recruiting und Online- Assessments. Manches war eher technologielastig, anderes mehr ein Kulturthema. Ich selber habe eine Session mitgeleitet zur Frage, in welche Richtung HR geht und ob der Business Partner noch das Modell ist. Und dann gab es mit dem Thema Guerilla-Lernen einen neuen Zugang zur Personalentwicklung.\n\nJannis Tsalikis: Das fand ich eine wirklich spannende Session. Es ging darum, dass man eben nicht klassisch denkt: ‚Wir müssen den Leuten jetzt das und das beibringen’, sondern dass man von der Zielgruppe aus denkt. Dass man sich überlegt, in welchen Situationen man die Leute am besten erreichen kann, um nicht in den alten Stil von Frontalunterricht zu verfallen.\n\nWas haben Sie außerdem noch als neu, als inspirierend wahrgenommen hier auf dem BarCamp? Oder war Ihnen alles schon bekannt?\n\nTsalikis: Wir als Veranstalter konnten natürlich gar nicht an allen Sessions teilnehmen. Aber dieses Guerilla-Lernen fand ich neu, darüber habe ich so noch nicht nachgedacht. Insgesamt ist es schön, dass es beim HR BarCamp eine gute Mischung gibt zwischen Dienstleistern und Praktikern, die Sessions geben.\n\nWarum braucht es denn so eine Tagung wie das HR BarCamp?\n\nAthanas: Es gibt einfach wenig Offline-Formate, die uns zugesagt haben, wo innovative Inhalte auch in innovativen Formaten diskutiert werden können.\n\nTsalikis: Vor allen Dingen waren wir es leid, den althergebrachten Stil der Konferenzen ertragen zu müssen. Man muss sich vergegenwärtigen, dass die Leute ja extrem beschäftigt sind und sich dann einen Tag freinehmen um Impulse zu bekommen. Und dann sind sie nach dem ersten Vortrag schon halb eingeschlafen, weil sie die Hälfte davon kennen, überhaupt nicht integriert werden und auch nicht unterhalten werden. So verliert man die Leute. Das kriegt man auf den Kongressen mit. Diese Zeit ist eigentlich auch vorbei. Gerade aufgrund der sozialen Medien gibt es Veränderungen, alles ist dialogischer geworden. Die Leute wollen miteinander reden und sich austauschen.\n\nDemnach ließe sich vermuten, dass es eher die jüngeren, online-affineren Personaler sind, die zum HR BarCamp kommen?\n\nAthanas: Das ist gemischt. Sicherlich ist der Altersschnitt hier schon eher jünger, aber das heißt nicht, dass hier nur die Generation Y dabei ist oder sich die Leute kollektiv bei Foursquare einchecken. Aufgeschlossen muss man sein. Aber das geht ja auch im höheren Alter.\n\nTsalikis: Es gab mal eine Debatte vor ein paar Jahren, wie altbacken und verstaubt doch die Personaler seien und das sie gar nicht in der Lage seien, Innovationen anzuschieben. Ich habe das nie so empfunden. Klar, ich bin auch in der Medienbranche tätig, da ist das eh eine ganz andere Sache. Aber auch auf Kongressen hab ich Leute kennengelernt, die in ihrem Fach Experten waren. Die haben viel zu tun, müssen sich ständig etwas Neues überlegen, viele von ihnen sind regelmäßig in Change-Situationen, bei denen sie zwischen Betriebsrat, Geschäftsführung und Mitarbeitern jonglieren müssen. Das ist eine Herausforderung. Vor allem wenn es auch noch Spaß machen soll.\n\nWie funktioniert denn die Organisation des HR BarCamps? Machen Sie das neben dem Hauptjob?\n\nTsalikis: Ja, das ist ein Hobby.\n\nAthanas: Das läuft tatsächlich nebenbei. Es bringt aber auch so viel Spaß, dass wir das gerne auf uns nehmen.\n\nTsalikis: Ich hab auch einen Arbeitgeber, der das toleriert und gut findet. In der Regel findet die Organisation am Abend oder am Wochenende statt, aber wenn ich dann mal eine Pause länger ausdehnen muss, weil Christoph und ich uns noch mal austauschen müssen, dann drückt der ein Auge zu.\n\nKönnen Sie schon einen Blick ins kommende Jahr werfen, wird es ein drittes HR BarCamp geben?\n\nTsalikis: Wir werden auf jeden Fall weitermachen. Das ist zwar für uns beide richtig anstrengend, aber es macht unglaublich Spaß und das Feedback ist super. Wir sind immer wieder überrascht, mit wie viel Begeisterung die Kollegen auf uns zukommen und sagen ‚Mensch das wurde aber auch Zeit’.\n\nAthanas: Wir waren in diesem Jahr in zwei Tagen ausgebucht. Das ist Wahnsinn. Es waren dann 140 Teilnehmer, was ich gut finde. So hat das BarCamp eine sehr persönliche Atmosphäre und man kann mit vielen Leuten reden. Ich denke, es wird also auch im kommenden Jahr ein BarCamp geben, da bleiben wir dran.",
    "text_deduped": "„Recruiting ist ein großes Thema“\n\nIm Februar hat in Berlin das zweite HR BarCamp stattgefunden. Die Organisatoren Christoph Athanas und Jannis Tsalikis über ihr Tagungskonzept und die diesjährigen Themen.\n\nHerr Athanas, Herr Tsalikis, die Personaler haben das Programm der Tagung selbst bestimmt. Welche Themen waren besonders präsent, gab es da Schwerpunkte?\n\nChristoph Athanas: Recruiting ist ein ganz großes Thema, da hatten wir Sessions wie Mobile Recruiting, transparentes Recruiting und Online- Assessments. Manches war eher technologielastig, anderes mehr ein Kulturthema. Ich selber habe eine Session mitgeleitet zur Frage, in welche Richtung HR geht und ob der Business Partner noch das Modell ist. Und dann gab es mit dem Thema Guerilla-Lernen einen neuen Zugang zur Personalentwicklung.\n\nJannis Tsalikis: Das fand ich eine wirklich spannende Session. Es ging darum, dass man eben nicht klassisch denkt: ‚Wir müssen den Leuten jetzt das und das beibringen’, sondern dass man von der Zielgruppe aus denkt. Dass man sich überlegt, in welchen Situationen man die Leute am besten erreichen kann, um nicht in den alten Stil von Frontalunterricht zu verfallen.\n\nWas haben Sie außerdem noch als neu, als inspirierend wahrgenommen hier auf dem BarCamp? Oder war Ihnen alles schon bekannt?\n\nTsalikis: Wir als Veranstalter konnten natürlich gar nicht an allen Sessions teilnehmen. Aber dieses Guerilla-Lernen fand ich neu, darüber habe ich so noch nicht nachgedacht. Insgesamt ist es schön, dass es beim HR BarCamp eine gute Mischung gibt zwischen Dienstleistern und Praktikern, die Sessions geben.\n\nWarum braucht es denn so eine Tagung wie das HR BarCamp?\n\nAthanas: Es gibt einfach wenig Offline-Formate, die uns zugesagt haben, wo innovative Inhalte auch in innovativen Formaten diskutiert werden können.\n\nTsalikis: Vor allen Dingen waren wir es leid, den althergebrachten Stil der Konferenzen ertragen zu müssen. Man muss sich vergegenwärtigen, dass die Leute ja extrem beschäftigt sind und sich dann einen Tag freinehmen um Impulse zu bekommen. Und dann sind sie nach dem ersten Vortrag schon halb eingeschlafen, weil sie die Hälfte davon kennen, überhaupt nicht integriert werden und auch nicht unterhalten werden. So verliert man die Leute. Das kriegt man auf den Kongressen mit. Diese Zeit ist eigentlich auch vorbei. Gerade aufgrund der sozialen Medien gibt es Veränderungen, alles ist dialogischer geworden. Die Leute wollen miteinander reden und sich austauschen.\n\nDemnach ließe sich vermuten, dass es eher die jüngeren, online-affineren Personaler sind, die zum HR BarCamp kommen?\n\nAthanas: Das ist gemischt. Sicherlich ist der Altersschnitt hier schon eher jünger, aber das heißt nicht, dass hier nur die Generation Y dabei ist oder sich die Leute kollektiv bei Foursquare einchecken. Aufgeschlossen muss man sein. Aber das geht ja auch im höheren Alter.\n\nTsalikis: Es gab mal eine Debatte vor ein paar Jahren, wie altbacken und verstaubt doch die Personaler seien und das sie gar nicht in der Lage seien, Innovationen anzuschieben. Ich habe das nie so empfunden. Klar, ich bin auch in der Medienbranche tätig, da ist das eh eine ganz andere Sache. Aber auch auf Kongressen hab ich Leute kennengelernt, die in ihrem Fach Experten waren. Die haben viel zu tun, müssen sich ständig etwas Neues überlegen, viele von ihnen sind regelmäßig in Change-Situationen, bei denen sie zwischen Betriebsrat, Geschäftsführung und Mitarbeitern jonglieren müssen. Das ist eine Herausforderung. Vor allem wenn es auch noch Spaß machen soll.\n\nWie funktioniert denn die Organisation des HR BarCamps? Machen Sie das neben dem Hauptjob?\n\nTsalikis: Ja, das ist ein Hobby.\n\nAthanas: Das läuft tatsächlich nebenbei. Es bringt aber auch so viel Spaß, dass wir das gerne auf uns nehmen.\n\nTsalikis: Ich hab auch einen Arbeitgeber, der das toleriert und gut findet. In der Regel findet die Organisation am Abend oder am Wochenende statt, aber wenn ich dann mal eine Pause länger ausdehnen muss, weil Christoph und ich uns noch mal austauschen müssen, dann drückt der ein Auge zu.\n\nKönnen Sie schon einen Blick ins kommende Jahr werfen, wird es ein drittes HR BarCamp geben?\n\nTsalikis: Wir werden auf jeden Fall weitermachen. Das ist zwar für uns beide richtig anstrengend, aber es macht unglaublich Spaß und das Feedback ist super. Wir sind immer wieder überrascht, mit wie viel Begeisterung die Kollegen auf uns zukommen und sagen ‚Mensch das wurde aber auch Zeit’.\n\nAthanas: Wir waren in diesem Jahr in zwei Tagen ausgebucht. Das ist Wahnsinn. Es waren dann 140 Teilnehmer, was ich gut finde. So hat das BarCamp eine sehr persönliche Atmosphäre und man kann mit vielen Leuten reden. Ich denke, es wird also auch im kommenden Jahr ein BarCamp geben, da bleiben wir dran.",
    "lemmas": [
        "--",
        "Recruiting",
        "sein",
        "ein",
        "groß",
        "Thema",
        "--",
        "\n\n",
        "in",
        "Februar",
        "haben",
        "in",
        "Berlin",
        "der",
        "zweiter",
        "HR",
        "BarCamp",
        "stattfinden",
        "--",
        "der",
        "Organisator",
        "Christoph",
        "Athanas",
        "und",
        "Jannis",
        "Tsalikis",
        "über",
        "ihr",
        "Tagungskonzept",
        "und",
        "der",
        "diesjährig",
        "Thema",
        "--",
        "\n\n",
        "Herr",
        "Athana",
        "--",
        "Herr",
        "Tsalikis",
        "--",
        "der",
        "Personaler",
        "haben",
        "der",
        "Programm",
        "der",
        "Tagung",
        "selbst",
        "bestimmen",
        "--",
        "welcher",
        "Thema",
        "sein",
        "besonders",
        "präsent",
        "--",
        "geben",
        "es",
        "da",
        "Schwerpunkt",
        "--",
        "\n\n",
        "Christoph",
        "Athanas",
        "--",
        "Recruiting",
        "sein",
        "ein",
        "ganz",
        "groß",
        "Thema",
        "--",
        "da",
        "haben",
        "wir",
        "Session",
        "wie",
        "mobil",
        "Recruiting",
        "--",
        "transparent",
        "Recruiting",
        "und",
        "Online",
        "Assessment",
        "--",
        "mancher",
        "sein",
        "eher",
        "technologielastig",
        "--",
        "anderer",
        "mehr",
        "ein",
        "Kulturthema",
        "--",
        "ich",
        "selber",
        "haben",
        "ein",
        "Session",
        "mitgeleiten",
        "zu",
        "Frage",
        "--",
        "in",
        "welcher",
        "Richtung",
        "HR",
        "gehen",
        "und",
        "ob",
        "der",
        "Business",
        "Partner",
        "noch",
        "der",
        "Modell",
        "sein",
        "--",
        "und",
        "dann",
        "geben",
        "es",
        "mit",
        "der",
        "Thema",
        "Guerilla-Lern",
        "ein",
        "neu",
        "Zugang",
        "zu",
        "Personalentwicklung",
        "--",
        "\n\n",
        "Jannis",
        "Tsalikis",
        "--",
        "der",
        "finden",
        "ich",
        "ein",
        "wirklich",
        "spannend",
        "Session",
        "--",
        "es",
        "gehen",
        "darum",
        "--",
        "dass",
        "man",
        "eben",
        "nicht",
        "klassisch",
        "denken",
        "--",
        "‚",
        "wir",
        "müssen",
        "der",
        "Leute",
        "jetzt",
        "der",
        "und",
        "der",
        "beibringen",
        "’-",
        "--",
        "sondern",
        "dass",
        "man",
        "von",
        "der",
        "Zielgruppe",
        "aus",
        "denken",
        "--",
        "dass",
        "man",
        "sich",
        "überlegen",
        "--",
        "in",
        "welcher",
        "Situation",
        "man",
        "der",
        "Leute",
        "am",
        "gut",
        "erreichen",
        "können",
        "--",
        "um",
        "nicht",
        "in",
        "der",
        "alt",
        "Stil",
        "von",
        "Frontalunterricht",
        "zu",
        "verfallen",
        "--",
        "\n\n",
        "was",
        "haben",
        "sie",
        "außerdem",
        "noch",
        "als",
        "neu",
        "--",
        "als",
        "inspirierend",
        "wahrnehmen",
        "hier",
        "auf",
        "der",
        "BarCamp",
        "--",
        "oder",
        "sein",
        "ihnen",
        "alle",
        "schon",
        "bekannt",
        "--",
        "\n\n",
        "Tsaliki",
        "--",
        "wir",
        "als",
        "Veranstalter",
        "können",
        "natürlich",
        "gar",
        "nicht",
        "an",
        "aller",
        "Session",
        "teilnehmen",
        "--",
        "aber",
        "dieser",
        "Guerilla-Lern",
        "finden",
        "ich",
        "neu",
        "--",
        "darüber",
        "haben",
        "ich",
        "so",
        "noch",
        "nicht",
        "nachdenken",
        "--",
        "insgesamt",
        "sein",
        "es",
        "schön",
        "--",
        "dass",
        "es",
        "bei",
        "HR",
        "BarCamp",
        "ein",
        "gut",
        "Mischung",
        "geben",
        "zwischen",
        "Dienstleister",
        "und",
        "Praktiker",
        "--",
        "der",
        "Session",
        "geben",
        "--",
        "\n\n",
        "warum",
        "brauchen",
        "es",
        "denn",
        "so",
        "ein",
        "Tagung",
        "wie",
        "der",
        "HR",
        "BarCamp",
        "--",
        "\n\n",
        "Athana",
        "--",
        "es",
        "geben",
        "einfach",
        "wenig",
        "Offline-Format",
        "--",
        "der",
        "uns",
        "zusagen",
        "haben",
        "--",
        "wo",
        "innovativ",
        "Inhalt",
        "auch",
        "in",
        "innovativ",
        "Format",
        "diskutieren",
        "werden",
        "können",
        "--",
        "\n\n",
        "Tsaliki",
        "--",
        "vor",
        "aller",
        "Ding",
        "sein",
        "wir",
        "es",
        "leid",
        "--",
        "der",
        "althergebracht",
        "Stil",
        "der",
        "Konferenz",
        "ertragen",
        "zu",
        "müssen",
        "--",
        "man",
        "muss",
        "sich",
        "vergegenwärtigen",
        "--",
        "dass",
        "der",
        "Leute",
        "ja",
        "extrem",
        "beschäftigen",
        "sein",
        "und",
        "sich",
        "dann",
        "ein",
        "Tag",
        "freinehmen",
        "um",
        "Impuls",
        "zu",
        "bekommen",
        "--",
        "und",
        "dann",
        "sein",
        "sie",
        "nach",
        "der",
        "erster",
        "Vortrag",
        "schon",
        "halb",
        "einschlafen",
        "--",
        "weil",
        "sie",
        "der",
        "Hälfte",
        "davon",
        "kennen",
        "--",
        "überhaupt",
        "nicht",
        "integrieren",
        "werden",
        "und",
        "auch",
        "nicht",
        "unterhalten",
        "werden",
        "--",
        "so",
        "verlieren",
        "man",
        "der",
        "Leute",
        "--",
        "der",
        "kriegen",
        "man",
        "auf",
        "der",
        "Kongress",
        "mit",
        "--",
        "dieser",
        "Zeit",
        "sein",
        "eigentlich",
        "auch",
        "vorbei",
        "--",
        "gerade",
        "aufgrund",
        "der",
        "sozial",
        "Medium",
        "geben",
        "es",
        "Veränderung",
        "--",
        "alle",
        "sein",
        "dialogisch",
        "werden",
        "--",
        "der",
        "Leute",
        "wollen",
        "miteinander",
        "reden",
        "und",
        "sich",
        "austauschen",
        "--",
        "\n\n",
        "demnach",
        "lassen",
        "sich",
        "vermuten",
        "--",
        "dass",
        "es",
        "eher",
        "der",
        "jung",
        "--",
        "online-affineren",
        "Personaler",
        "sein",
        "--",
        "der",
        "zu",
        "HR",
        "BarCamp",
        "kommen",
        "--",
        "\n\n",
        "Athana",
        "--",
        "der",
        "sein",
        "mischen",
        "--",
        "sicherlich",
        "sein",
        "der",
        "Altersschnitt",
        "hier",
        "schon",
        "eher",
        "jung",
        "--",
        "aber",
        "der",
        "heißen",
        "nicht",
        "--",
        "dass",
        "hier",
        "nur",
        "der",
        "Generation",
        "Y",
        "dabei",
        "sein",
        "oder",
        "sich",
        "der",
        "Leute",
        "kollektiv",
        "bei",
        "Foursquare",
        "einchecken",
        "--",
        "Aufgeschlossen",
        "muss",
        "man",
        "sein",
        "--",
        "aber",
        "der",
        "gehen",
        "ja",
        "auch",
        "in",
        "hoch",
        "Alter",
        "--",
        "\n\n",
        "Tsalikis",
        "--",
        "es",
        "geben",
        "mal",
        "ein",
        "Debatte",
        "vor",
        "ein",
        "paar",
        "Jahr",
        "--",
        "wie",
        "altbacken",
        "und",
        "verstauben",
        "doch",
        "der",
        "Personaler",
        "sein",
        "und",
        "der",
        "sie",
        "gar",
        "nicht",
        "in",
        "der",
        "Lage",
        "sein",
        "--",
        "Innovation",
        "anschieben",
        "--",
        "ich",
        "haben",
        "der",
        "nie",
        "so",
        "empfinden",
        "--",
        "klar",
        "--",
        "ich",
        "sein",
        "auch",
        "in",
        "der",
        "Medienbranche",
        "tätig",
        "--",
        "da",
        "sein",
        "der",
        "eh",
        "ein",
        "ganz",
        "anderer",
        "Sache",
        "--",
        "aber",
        "auch",
        "auf",
        "Kongress",
        "hab",
        "ich",
        "Leute",
        "kennenlernen",
        "--",
        "der",
        "in",
        "ihr",
        "Fach",
        "Experte",
        "sein",
        "--",
        "der",
        "haben",
        "viel",
        "zu",
        "tun",
        "--",
        "müssen",
        "sich",
        "ständig",
        "etwas",
        "neue",
        "überlegen",
        "--",
        "viele",
        "von",
        "ihnen",
        "sein",
        "regelmäßig",
        "in",
        "Change-Situation",
        "--",
        "bei",
        "der",
        "sie",
        "zwischen",
        "Betriebsrat",
        "--",
        "Geschäftsführung",
        "und",
        "Mitarbeiter",
        "jonglieren",
        "müssen",
        "--",
        "der",
        "sein",
        "ein",
        "Herausforderung",
        "--",
        "vor",
        "alle",
        "wenn",
        "es",
        "auch",
        "noch",
        "Spaß",
        "machen",
        "sollen",
        "--",
        "\n\n",
        "wie",
        "funktionieren",
        "denn",
        "der",
        "Organisation",
        "der",
        "HR",
        "BarCamp",
        "--",
        "machen",
        "sie",
        "der",
        "neben",
        "der",
        "Hauptjob",
        "--",
        "\n\n",
        "Tsaliki",
        "--",
        "ja",
        "--",
        "der",
        "sein",
        "ein",
        "Hobby",
        "--",
        "\n\n",
        "Athana",
        "--",
        "der",
        "laufen",
        "tatsächlich",
        "nebenbei",
        "--",
        "es",
        "bringen",
        "aber",
        "auch",
        "so",
        "viel",
        "Spaß",
        "--",
        "dass",
        "wir",
        "der",
        "gerne",
        "auf",
        "uns",
        "nehmen",
        "--",
        "\n\n",
        "Tsaliki",
        "--",
        "ich",
        "hab",
        "auch",
        "ein",
        "Arbeitgeber",
        "--",
        "der",
        "der",
        "tolerieren",
        "und",
        "gut",
        "finden",
        "--",
        "in",
        "der",
        "Regel",
        "finden",
        "der",
        "Organisation",
        "an",
        "Abend",
        "oder",
        "an",
        "Wochenende",
        "statt",
        "--",
        "aber",
        "wenn",
        "ich",
        "dann",
        "mal",
        "ein",
        "Pause",
        "lang",
        "ausdehnen",
        "muss",
        "--",
        "weil",
        "Christoph",
        "und",
        "ich",
        "sich",
        "noch",
        "mal",
        "austauschen",
        "müssen",
        "--",
        "dann",
        "drücken",
        "der",
        "ein",
        "Auge",
        "zu",
        "--",
        "\n\n",
        "können",
        "sie",
        "schon",
        "ein",
        "Blick",
        "in",
        "kommend",
        "Jahr",
        "werfen",
        "--",
        "werden",
        "es",
        "ein",
        "dritter",
        "HR",
        "BarCamp",
        "geben",
        "--",
        "\n\n",
        "Tsaliki",
        "--",
        "wir",
        "werden",
        "auf",
        "jeder",
        "Fall",
        "weitermachen",
        "--",
        "der",
        "sein",
        "zwar",
        "für",
        "uns",
        "beide",
        "richtig",
        "anstrengend",
        "--",
        "aber",
        "es",
        "machen",
        "unglaublich",
        "Spaß",
        "und",
        "der",
        "Feedback",
        "sein",
        "super",
        "--",
        "wir",
        "sein",
        "immer",
        "wieder",
        "überraschen",
        "--",
        "mit",
        "wie",
        "viel",
        "Begeisterung",
        "der",
        "Kollege",
        "auf",
        "uns",
        "zukommen",
        "und",
        "sagen",
        "‚",
        "Mensch",
        "der",
        "werden",
        "aber",
        "auch",
        "Zeit",
        "’",
        "--",
        "\n\n",
        "Athana",
        "--",
        "wir",
        "sein",
        "in",
        "dieser",
        "Jahr",
        "in",
        "zwei",
        "Tag",
        "ausbuchen",
        "--",
        "der",
        "sein",
        "Wahnsinn",
        "--",
        "es",
        "sein",
        "dann",
        "140",
        "Teilnehmer",
        "--",
        "was",
        "ich",
        "gut",
        "finden",
        "--",
        "so",
        "haben",
        "der",
        "BarCamp",
        "ein",
        "sehr",
        "persönlich",
        "Atmosphäre",
        "und",
        "man",
        "können",
        "mit",
        "vieler",
        "Leute",
        "reden",
        "--",
        "ich",
        "denken",
        "--",
        "es",
        "werden",
        "also",
        "auch",
        "in",
        "kommend",
        "Jahr",
        "ein",
        "BarCamp",
        "geben",
        "--",
        "da",
        "bleiben",
        "wir",
        "dran",
        "--"
    ],
    "token": [
        "„",
        "Recruiting",
        "ist",
        "ein",
        "großes",
        "Thema",
        "“",
        "\n\n",
        "Im",
        "Februar",
        "hat",
        "in",
        "Berlin",
        "das",
        "zweite",
        "HR",
        "BarCamp",
        "stattgefunden",
        ".",
        "Die",
        "Organisatoren",
        "Christoph",
        "Athanas",
        "und",
        "Jannis",
        "Tsalikis",
        "über",
        "ihr",
        "Tagungskonzept",
        "und",
        "die",
        "diesjährigen",
        "Themen",
        ".",
        "\n\n",
        "Herr",
        "Athanas",
        ",",
        "Herr",
        "Tsalikis",
        ",",
        "die",
        "Personaler",
        "haben",
        "das",
        "Programm",
        "der",
        "Tagung",
        "selbst",
        "bestimmt",
        ".",
        "Welche",
        "Themen",
        "waren",
        "besonders",
        "präsent",
        ",",
        "gab",
        "es",
        "da",
        "Schwerpunkte",
        "?",
        "\n\n",
        "Christoph",
        "Athanas",
        ":",
        "Recruiting",
        "ist",
        "ein",
        "ganz",
        "großes",
        "Thema",
        ",",
        "da",
        "hatten",
        "wir",
        "Sessions",
        "wie",
        "Mobile",
        "Recruiting",
        ",",
        "transparentes",
        "Recruiting",
        "und",
        "Online-",
        "Assessments",
        ".",
        "Manches",
        "war",
        "eher",
        "technologielastig",
        ",",
        "anderes",
        "mehr",
        "ein",
        "Kulturthema",
        ".",
        "Ich",
        "selber",
        "habe",
        "eine",
        "Session",
        "mitgeleitet",
        "zur",
        "Frage",
        ",",
        "in",
        "welche",
        "Richtung",
        "HR",
        "geht",
        "und",
        "ob",
        "der",
        "Business",
        "Partner",
        "noch",
        "das",
        "Modell",
        "ist",
        ".",
        "Und",
        "dann",
        "gab",
        "es",
        "mit",
        "dem",
        "Thema",
        "Guerilla-Lernen",
        "einen",
        "neuen",
        "Zugang",
        "zur",
        "Personalentwicklung",
        ".",
        "\n\n",
        "Jannis",
        "Tsalikis",
        ":",
        "Das",
        "fand",
        "ich",
        "eine",
        "wirklich",
        "spannende",
        "Session",
        ".",
        "Es",
        "ging",
        "darum",
        ",",
        "dass",
        "man",
        "eben",
        "nicht",
        "klassisch",
        "denkt",
        ":",
        "‚",
        "Wir",
        "müssen",
        "den",
        "Leuten",
        "jetzt",
        "das",
        "und",
        "das",
        "beibringen",
        "’",
        ",",
        "sondern",
        "dass",
        "man",
        "von",
        "der",
        "Zielgruppe",
        "aus",
        "denkt",
        ".",
        "Dass",
        "man",
        "sich",
        "überlegt",
        ",",
        "in",
        "welchen",
        "Situationen",
        "man",
        "die",
        "Leute",
        "am",
        "besten",
        "erreichen",
        "kann",
        ",",
        "um",
        "nicht",
        "in",
        "den",
        "alten",
        "Stil",
        "von",
        "Frontalunterricht",
        "zu",
        "verfallen",
        ".",
        "\n\n",
        "Was",
        "haben",
        "Sie",
        "außerdem",
        "noch",
        "als",
        "neu",
        ",",
        "als",
        "inspirierend",
        "wahrgenommen",
        "hier",
        "auf",
        "dem",
        "BarCamp",
        "?",
        "Oder",
        "war",
        "Ihnen",
        "alles",
        "schon",
        "bekannt",
        "?",
        "\n\n",
        "Tsalikis",
        ":",
        "Wir",
        "als",
        "Veranstalter",
        "konnten",
        "natürlich",
        "gar",
        "nicht",
        "an",
        "allen",
        "Sessions",
        "teilnehmen",
        ".",
        "Aber",
        "dieses",
        "Guerilla-Lernen",
        "fand",
        "ich",
        "neu",
        ",",
        "darüber",
        "habe",
        "ich",
        "so",
        "noch",
        "nicht",
        "nachgedacht",
        ".",
        "Insgesamt",
        "ist",
        "es",
        "schön",
        ",",
        "dass",
        "es",
        "beim",
        "HR",
        "BarCamp",
        "eine",
        "gute",
        "Mischung",
        "gibt",
        "zwischen",
        "Dienstleistern",
        "und",
        "Praktikern",
        ",",
        "die",
        "Sessions",
        "geben",
        ".",
        "\n\n",
        "Warum",
        "braucht",
        "es",
        "denn",
        "so",
        "eine",
        "Tagung",
        "wie",
        "das",
        "HR",
        "BarCamp",
        "?",
        "\n\n",
        "Athanas",
        ":",
        "Es",
        "gibt",
        "einfach",
        "wenig",
        "Offline-Formate",
        ",",
        "die",
        "uns",
        "zugesagt",
        "haben",
        ",",
        "wo",
        "innovative",
        "Inhalte",
        "auch",
        "in",
        "innovativen",
        "Formaten",
        "diskutiert",
        "werden",
        "können",
        ".",
        "\n\n",
        "Tsalikis",
        ":",
        "Vor",
        "allen",
        "Dingen",
        "waren",
        "wir",
        "es",
        "leid",
        ",",
        "den",
        "althergebrachten",
        "Stil",
        "der",
        "Konferenzen",
        "ertragen",
        "zu",
        "müssen",
        ".",
        "Man",
        "muss",
        "sich",
        "vergegenwärtigen",
        ",",
        "dass",
        "die",
        "Leute",
        "ja",
        "extrem",
        "beschäftigt",
        "sind",
        "und",
        "sich",
        "dann",
        "einen",
        "Tag",
        "freinehmen",
        "um",
        "Impulse",
        "zu",
        "bekommen",
        ".",
        "Und",
        "dann",
        "sind",
        "sie",
        "nach",
        "dem",
        "ersten",
        "Vortrag",
        "schon",
        "halb",
        "eingeschlafen",
        ",",
        "weil",
        "sie",
        "die",
        "Hälfte",
        "davon",
        "kennen",
        ",",
        "überhaupt",
        "nicht",
        "integriert",
        "werden",
        "und",
        "auch",
        "nicht",
        "unterhalten",
        "werden",
        ".",
        "So",
        "verliert",
        "man",
        "die",
        "Leute",
        ".",
        "Das",
        "kriegt",
        "man",
        "auf",
        "den",
        "Kongressen",
        "mit",
        ".",
        "Diese",
        "Zeit",
        "ist",
        "eigentlich",
        "auch",
        "vorbei",
        ".",
        "Gerade",
        "aufgrund",
        "der",
        "sozialen",
        "Medien",
        "gibt",
        "es",
        "Veränderungen",
        ",",
        "alles",
        "ist",
        "dialogischer",
        "geworden",
        ".",
        "Die",
        "Leute",
        "wollen",
        "miteinander",
        "reden",
        "und",
        "sich",
        "austauschen",
        ".",
        "\n\n",
        "Demnach",
        "ließe",
        "sich",
        "vermuten",
        ",",
        "dass",
        "es",
        "eher",
        "die",
        "jüngeren",
        ",",
        "online-affineren",
        "Personaler",
        "sind",
        ",",
        "die",
        "zum",
        "HR",
        "BarCamp",
        "kommen",
        "?",
        "\n\n",
        "Athanas",
        ":",
        "Das",
        "ist",
        "gemischt",
        ".",
        "Sicherlich",
        "ist",
        "der",
        "Altersschnitt",
        "hier",
        "schon",
        "eher",
        "jünger",
        ",",
        "aber",
        "das",
        "heißt",
        "nicht",
        ",",
        "dass",
        "hier",
        "nur",
        "die",
        "Generation",
        "Y",
        "dabei",
        "ist",
        "oder",
        "sich",
        "die",
        "Leute",
        "kollektiv",
        "bei",
        "Foursquare",
        "einchecken",
        ".",
        "Aufgeschlossen",
        "muss",
        "man",
        "sein",
        ".",
        "Aber",
        "das",
        "geht",
        "ja",
        "auch",
        "im",
        "höheren",
        "Alter",
        ".",
        "\n\n",
        "Tsalikis",
        ":",
        "Es",
        "gab",
        "mal",
        "eine",
        "Debatte",
        "vor",
        "ein",
        "paar",
        "Jahren",
        ",",
        "wie",
        "altbacken",
        "und",
        "verstaubt",
        "doch",
        "die",
        "Personaler",
        "seien",
        "und",
        "das",
        "sie",
        "gar",
        "nicht",
        "in",
        "der",
        "Lage",
        "seien",
        ",",
        "Innovationen",
        "anzuschieben",
        ".",
        "Ich",
        "habe",
        "das",
        "nie",
        "so",
        "empfunden",
        ".",
        "Klar",
        ",",
        "ich",
        "bin",
        "auch",
        "in",
        "der",
        "Medienbranche",
        "tätig",
        ",",
        "da",
        "ist",
        "das",
        "eh",
        "eine",
        "ganz",
        "andere",
        "Sache",
        ".",
        "Aber",
        "auch",
        "auf",
        "Kongressen",
        "hab",
        "ich",
        "Leute",
        "kennengelernt",
        ",",
        "die",
        "in",
        "ihrem",
        "Fach",
        "Experten",
        "waren",
        ".",
        "Die",
        "haben",
        "viel",
        "zu",
        "tun",
        ",",
        "müssen",
        "sich",
        "ständig",
        "etwas",
        "Neues",
        "überlegen",
        ",",
        "viele",
        "von",
        "ihnen",
        "sind",
        "regelmäßig",
        "in",
        "Change-Situationen",
        ",",
        "bei",
        "denen",
        "sie",
        "zwischen",
        "Betriebsrat",
        ",",
        "Geschäftsführung",
        "und",
        "Mitarbeitern",
        "jonglieren",
        "müssen",
        ".",
        "Das",
        "ist",
        "eine",
        "Herausforderung",
        ".",
        "Vor",
        "allem",
        "wenn",
        "es",
        "auch",
        "noch",
        "Spaß",
        "machen",
        "soll",
        ".",
        "\n\n",
        "Wie",
        "funktioniert",
        "denn",
        "die",
        "Organisation",
        "des",
        "HR",
        "BarCamps",
        "?",
        "Machen",
        "Sie",
        "das",
        "neben",
        "dem",
        "Hauptjob",
        "?",
        "\n\n",
        "Tsalikis",
        ":",
        "Ja",
        ",",
        "das",
        "ist",
        "ein",
        "Hobby",
        ".",
        "\n\n",
        "Athanas",
        ":",
        "Das",
        "läuft",
        "tatsächlich",
        "nebenbei",
        ".",
        "Es",
        "bringt",
        "aber",
        "auch",
        "so",
        "viel",
        "Spaß",
        ",",
        "dass",
        "wir",
        "das",
        "gerne",
        "auf",
        "uns",
        "nehmen",
        ".",
        "\n\n",
        "Tsalikis",
        ":",
        "Ich",
        "hab",
        "auch",
        "einen",
        "Arbeitgeber",
        ",",
        "der",
        "das",
        "toleriert",
        "und",
        "gut",
        "findet",
        ".",
        "In",
        "der",
        "Regel",
        "findet",
        "die",
        "Organisation",
        "am",
        "Abend",
        "oder",
        "am",
        "Wochenende",
        "statt",
        ",",
        "aber",
        "wenn",
        "ich",
        "dann",
        "mal",
        "eine",
        "Pause",
        "länger",
        "ausdehnen",
        "muss",
        ",",
        "weil",
        "Christoph",
        "und",
        "ich",
        "uns",
        "noch",
        "mal",
        "austauschen",
        "müssen",
        ",",
        "dann",
        "drückt",
        "der",
        "ein",
        "Auge",
        "zu",
        ".",
        "\n\n",
        "Können",
        "Sie",
        "schon",
        "einen",
        "Blick",
        "ins",
        "kommende",
        "Jahr",
        "werfen",
        ",",
        "wird",
        "es",
        "ein",
        "drittes",
        "HR",
        "BarCamp",
        "geben",
        "?",
        "\n\n",
        "Tsalikis",
        ":",
        "Wir",
        "werden",
        "auf",
        "jeden",
        "Fall",
        "weitermachen",
        ".",
        "Das",
        "ist",
        "zwar",
        "für",
        "uns",
        "beide",
        "richtig",
        "anstrengend",
        ",",
        "aber",
        "es",
        "macht",
        "unglaublich",
        "Spaß",
        "und",
        "das",
        "Feedback",
        "ist",
        "super",
        ".",
        "Wir",
        "sind",
        "immer",
        "wieder",
        "überrascht",
        ",",
        "mit",
        "wie",
        "viel",
        "Begeisterung",
        "die",
        "Kollegen",
        "auf",
        "uns",
        "zukommen",
        "und",
        "sagen",
        "‚",
        "Mensch",
        "das",
        "wurde",
        "aber",
        "auch",
        "Zeit",
        "’",
        ".",
        "\n\n",
        "Athanas",
        ":",
        "Wir",
        "waren",
        "in",
        "diesem",
        "Jahr",
        "in",
        "zwei",
        "Tagen",
        "ausgebucht",
        ".",
        "Das",
        "ist",
        "Wahnsinn",
        ".",
        "Es",
        "waren",
        "dann",
        "140",
        "Teilnehmer",
        ",",
        "was",
        "ich",
        "gut",
        "finde",
        ".",
        "So",
        "hat",
        "das",
        "BarCamp",
        "eine",
        "sehr",
        "persönliche",
        "Atmosphäre",
        "und",
        "man",
        "kann",
        "mit",
        "vielen",
        "Leuten",
        "reden",
        ".",
        "Ich",
        "denke",
        ",",
        "es",
        "wird",
        "also",
        "auch",
        "im",
        "kommenden",
        "Jahr",
        "ein",
        "BarCamp",
        "geben",
        ",",
        "da",
        "bleiben",
        "wir",
        "dran",
        "."
    ]
}